auto_modules.py
src/__init__.py
src/auto_modules.py
src/command.py
Flask_auto_modules-1.0.dist-info/LICENSE
Flask_auto_modules-1.0.dist-info/METADATA
Flask_auto_modules-1.0.dist-info/WHEEL
Flask_auto_modules-1.0.dist-info/entry_points.txt
Flask_auto_modules-1.0.dist-info/top_level.txt
Flask_auto_modules-1.0.dist-info/RECORD
