Metadata-Version: 2.1
Name: Flask-auto-modules
Version: 1.0
Summary: Auto modules install
Home-page: https://github.com/Rinat93/flak-auto-modules
Author: Zakirjanov Rinat
Author-email: rinat643@gmail.com
License: BSD
Platform: any
Classifier: Environment :: Web Environment
Classifier: Intended Audience :: Developers
Classifier: License :: OSI Approved :: MIT License
Classifier: Operating System :: OS Independent
Classifier: Programming Language :: Python :: 3
Classifier: Topic :: Internet :: WWW/HTTP :: Dynamic Content
Classifier: Topic :: Software Development :: Libraries :: Python Modules
Requires-Dist: Flask
